README
setup.py
templatefinder/__init__.py
templatefinder/template_loader.py
templatefinder.egg-info/PKG-INFO
templatefinder.egg-info/SOURCES.txt
templatefinder.egg-info/dependency_links.txt
templatefinder.egg-info/requires.txt
templatefinder.egg-info/top_level.txt
tests/test_app/__init__.py