Metadata-Version: 1.0
Name: templatefinder
Version: 0.1
Summary: Simple template loader for Django
Home-page: https://github.com/WhiskeyMedia/django-templatefinder
Author: Honza Kral
Author-email: honza.kral@gmail.com
License: BSD
Platform: UNKNOWN
Classifier: Development Status :: 4 - Beta
Classifier: Intended Audience :: Developers
Classifier: License :: OSI Approved :: BSD License
Classifier: Operating System :: OS Independent
Classifier: Framework :: Django
Classifier: Programming Language :: Python :: 2.5
Classifier: Programming Language :: Python :: 2.6
Classifier: Programming Language :: Python :: 2.7
Classifier: Topic :: Software Development :: Libraries :: Python Modules
